pochi/__init__.py
pochi/backends.py
pochi/backends_helpers.py
pochi/bridge.py
pochi/cli.py
pochi/commands.py
pochi/config.py
pochi/engines.py
pochi/events.py
pochi/logging.py
pochi/manager.py
pochi/markdown.py
pochi/model.py
pochi/orchestrator.py
pochi/presenter.py
pochi/progress.py
pochi/render.py
pochi/router.py
pochi/runner.py
pochi/runner_bridge.py
pochi/runners/__init__.py
pochi/runners/claude.py
pochi/runners/codex.py
pochi/runners/mock.py
pochi/runners/opencode.py
pochi/runners/pi.py
pochi/scheduler.py
pochi/schemas/__init__.py
pochi/schemas/claude.py
pochi/schemas/codex.py
pochi/schemas/opencode.py
pochi/schemas/pi.py
pochi/telegram/__init__.py
pochi/telegram/bridge.py
pochi/telegram/client.py
pochi/telegram/commands.py
pochi/telegram/presenter.py
pochi/telegram/render.py
pochi/telegram/transport.py
pochi/telegram.py
pochi/transport.py
pochi/utils/__init__.py
pochi/utils/paths.py
pochi/utils/streams.py
pochi/utils/subprocess.py
pochi/workspace/__init__.py
pochi/workspace/bridge.py
pochi/workspace/commands.py
pochi/workspace/config.py
pochi/workspace/manager.py
pochi/workspace/orchestrator.py
pochi/workspace/ralph.py
pochi/workspace/router.py
pochi-0.1.3.dist-info/WHEEL
pochi-0.1.3.dist-info/entry_points.txt
pochi-0.1.3.dist-info/METADATA
pochi-0.1.3.dist-info/RECORD
