Metadata-Version: 2.3
Name: pochi
Version: 0.1.3
Summary: Multi-model AI agent Telegram bot for multi-folder workspaces.
Author: asianviking
License: MIT License
Classifier: License :: OSI Approved :: MIT License
Classifier: Programming Language :: Python :: 3
Classifier: Programming Language :: Python :: 3.14
Classifier: Programming Language :: Python :: 3 :: Only
Classifier: Operating System :: OS Independent
Requires-Dist: anyio>=4.12.0
Requires-Dist: httpx>=0.28.1
Requires-Dist: markdown-it-py
Requires-Dist: msgspec>=0.20.0
Requires-Dist: structlog>=25.5.0
Requires-Dist: sulguk>=0.11.1
Requires-Dist: typer>=0.21.0
Requires-Python: >=3.14
Project-URL: Homepage, https://github.com/asianviking/pochi
Project-URL: Issues, https://github.com/asianviking/pochi/issues
Project-URL: Repository, https://github.com/asianviking/pochi
